HawkesPyLib/__init__.py
HawkesPyLib/inference.py
HawkesPyLib/processes.py
HawkesPyLib/simulation.py
HawkesPyLib/util.py
HawkesPyLib/core/__init__.py
HawkesPyLib/core/compensator.py
HawkesPyLib/core/intensity.py
HawkesPyLib/core/kernel.py
HawkesPyLib/core/logll.py
HawkesPyLib/core/simulation.py
HawkesPyLib-0.2.2.dist-info/LICENSE
HawkesPyLib-0.2.2.dist-info/METADATA
HawkesPyLib-0.2.2.dist-info/WHEEL
HawkesPyLib-0.2.2.dist-info/top_level.txt
HawkesPyLib-0.2.2.dist-info/RECORD
