Metadata-Version: 2.1
Name: HawkesPyLib
Version: 0.2.2
Summary: Python library for simulation and inference of Hawkes processes
Author: Simon Grimm
License: MIT
Project-URL: Homepage, https://simbold.github.io/HawkesPyLib/
Project-URL: Source, https://github.com/Simbold/HawkesPyLib
Keywords: hawkes,hawkes-process,point-process
Classifier: License :: OSI Approved :: MIT License
Classifier: Natural Language :: English
Classifier: Operating System :: OS Independent
Classifier: Programming Language :: Python :: 3
Classifier: Programming Language :: Python :: 3 :: Only
Classifier: Programming Language :: Python :: 3.8
Classifier: Programming Language :: Python :: 3.9
Classifier: Programming Language :: Python :: 3.10
Classifier: Programming Language :: Python :: 3.11
Classifier: Intended Audience :: Developers
Classifier: Intended Audience :: Science/Research
Requires-Python: >=3.8
License-File: LICENSE
Requires-Dist: numba (>=0.56)
Requires-Dist: numpy (>=1.23)
Requires-Dist: scipy (>=1.9)
Provides-Extra: testing
Requires-Dist: pytest (>=7.2) ; extra == 'testing'
Requires-Dist: flake8 (>=3.9) ; extra == 'testing'
Requires-Dist: tox (>=3.24) ; extra == 'testing'
